[
  {
    "model": "main.producttag",
    "fields": {
      "name": "Flutter",
      "slug": "flutter",
      "description": "",
      "active": true
    }
  },
  {
    "model": "main.producttag",
    "fields": {
      "name": "Technical",
      "slug": "technical",
      "description": "",
      "active": true
    }
  },
  {
    "model": "main.producttag",
    "fields": {
      "name": "Non-Fiction",
      "slug": "non-fiction",
      "description": "",
      "active": true
    }
  },
  {
    "model": "main.producttag",
    "fields": {
      "name": "Fiction",
      "slug": "fiction",
      "description": "",
      "active": true
    }
  },
  {
    "model": "main.producttag",
    "fields": {
      "name": "Mobile Development",
      "slug": "mobile-development",
      "description": "",
      "active": true
    }
  },
  {
    "model": "main.producttag",
    "fields": {
      "name": "Dart",
      "slug": "dart",
      "description": "",
      "active": true
    }
  }
]
